graphnet/__init__.py
graphnet/components.py
graphnet/exceptions.py
graphnet/graph.py
graphnet/utils.py
graphnet/_vis/__init__.py
graphnet/_vis/decorators.py
graphnet/_vis/layout.py
graphnet/algorithms/__init__.py
graphnet/algorithms/_search.py
graphnet/algorithms/_sort.py
graphnet/algorithms/path.py
graphnet-0.1.2.dist-info/LICENSE
graphnet-0.1.2.dist-info/METADATA
graphnet-0.1.2.dist-info/WHEEL
graphnet-0.1.2.dist-info/top_level.txt
graphnet-0.1.2.dist-info/RECORD
