Metadata-Version: 2.1
Name: graphnet
Version: 0.1.2
Summary: A python library for graph manipulation and visualization
Home-page: https://github.com/Fredpwol/graphnet
Author: Fredrick Pwol
Author-email: fredpwol@gmail.com
License: UNKNOWN
Platform: UNKNOWN
Classifier: License :: OSI Approved :: MIT License
Classifier: Programming Language :: Python :: 3
Classifier: Programming Language :: Python :: 3.5
Classifier: Programming Language :: Python :: 3.6
Classifier: Programming Language :: Python :: 3.7
Classifier: Programming Language :: Python :: 3.8
Classifier: Programming Language :: Python :: 3 :: Only
Requires-Dist: numpy
Requires-Dist: matplotlib
